AUTHORS.rst
CONTRIBUTING.rst
HISTORY.rst
LICENSE
MANIFEST.in
README.rst
setup.cfg
setup.py
dj_n3_templateplugins/__init__.py
dj_n3_templateplugins/admin.py
dj_n3_templateplugins/apps.py
dj_n3_templateplugins/decorators.py
dj_n3_templateplugins/models.py
dj_n3_templateplugins/plugin.py
dj_n3_templateplugins/urls.py
dj_n3_templateplugins/utils.py
dj_n3_templateplugins/views.py
dj_n3_templateplugins.egg-info/PKG-INFO
dj_n3_templateplugins.egg-info/SOURCES.txt
dj_n3_templateplugins.egg-info/dependency_links.txt
dj_n3_templateplugins.egg-info/not-zip-safe
dj_n3_templateplugins.egg-info/top_level.txt
dj_n3_templateplugins/migrations/0001_initial.py
dj_n3_templateplugins/migrations/__init__.py
dj_n3_templateplugins/static/css/dj_n3_templateplugins.css
dj_n3_templateplugins/static/js/dj_n3_templateplugins.js
dj_n3_templateplugins/templates/dj_n3_templateplugins/base.html
dj_n3_templateplugins/templatetags/render_plugin.py