Metadata-Version: 1.1
Name: dj-n3-templateplugins
Version: 0.3.1
Summary: Extensible Template Plugins for Django
Home-page: https://github.com/Jaredn/dj-n3-templateplugins
Author: Jared Newell
Author-email: jared.newell@gmail.com
License: MIT
Download-URL: https://github.com/Jaredn/dj-n3-templateplugins/archive/0.3.1.tar.giz
Keywords: dj-n3-templateplugins django plugins template templateplugin
Platform: UNKNOWN
Classifier: Development Status :: 3 - Alpha
Classifier: Framework :: Django
Classifier: Framework :: Django :: 1.10
Classifier: Intended Audience :: Developers
Classifier: License :: OSI Approved :: BSD License
Classifier: Natural Language :: English
Classifier: Programming Language :: Python :: 2
Classifier: Programming Language :: Python :: 2.7
Classifier: Programming Language :: Python :: 3
Classifier: Programming Language :: Python :: 3.4
Classifier: Programming Language :: Python :: 3.5
